podenv/__init__.py
podenv/main.py
podenv/podenv.sh
podenv-0.1.3.dist-info/METADATA
podenv-0.1.3.dist-info/WHEEL
podenv-0.1.3.dist-info/entry_points.txt
podenv-0.1.3.dist-info/top_level.txt
podenv-0.1.3.dist-info/RECORD
