Metadata-Version: 2.1
Name: podenv
Version: 0.1.3
Summary: TPU Cluster Interactive Initialization Tool
Author-email: eagle-cyber <hainuo.cv.wang@gmail.com>
License: MIT
Project-URL: Homepage, https://github.com/yourusername/podenv
Keywords: tpu,cluster,initialization,ssh
Classifier: Development Status :: 3 - Alpha
Classifier: Intended Audience :: Developers
Classifier: License :: OSI Approved :: MIT License
Classifier: Operating System :: POSIX :: Linux
Classifier: Programming Language :: Python :: 3
Classifier: Programming Language :: Python :: 3.7
Classifier: Programming Language :: Python :: 3.8
Classifier: Programming Language :: Python :: 3.9
Classifier: Programming Language :: Python :: 3.10
Classifier: Programming Language :: Python :: 3.11
Requires-Python: >=3.7
